edmine/__init__.py
edmine/config/__init__.py
edmine/config/basic.py
edmine/config/data.py
edmine/config/env.py
edmine/config/model.py
edmine/config/train.py
edmine/constant/__init__.py
edmine/constant/kt_dataset.py
edmine/data/FileManager.py
edmine/data/KTDataProcessor.py
edmine/data/__init__.py
edmine/dataset/CognitiveDiagnosisDataset.py
edmine/dataset/KG4EXDataset.py
edmine/dataset/NonSequentialKTDataset.py
edmine/dataset/Sampler.py
edmine/dataset/SequentialKTDataset.py
edmine/dataset/SequentialKTDatasetWithSample.py
edmine/dataset/__init__.py
edmine/dataset/split_dataset.py
edmine/dataset/split_seq.py
edmine/env/__init__.py
edmine/env/learning_path_recommendation/KTEnv.py
edmine/env/learning_path_recommendation/__init__.py
edmine/evaluator/DLCDEvaluator.py
edmine/evaluator/DLEREvaluator.py
edmine/evaluator/DLEvaluator.py
edmine/evaluator/LPREvaluator.py
edmine/evaluator/SequentialDLKTEvaluator.py
edmine/evaluator/SequentialDLKTEvaluator4FTAcc.py
edmine/evaluator/__init__.py
edmine/llm/__init__.py
edmine/llm/dspy/__init__.py
edmine/llm/dspy/remote_llm/BaiLian.py
edmine/llm/dspy/remote_llm/GLM.py
edmine/llm/dspy/remote_llm/__init__.py
edmine/metric/__init__.py
edmine/metric/exercise_recommendation.py
edmine/metric/knowledge_tracing.py
edmine/metric/learning_path_recommendation.py
edmine/model/CognitiveDiagnosisModel.py
edmine/model/ExerciseRecommendationModel.py
edmine/model/KnowledgeTracingModel.py
edmine/model/LearningPathRecommendationAgent.py
edmine/model/__init__.py
edmine/model/load_agent.py
edmine/model/load_model.py
edmine/model/loss.py
edmine/model/registry.py
edmine/model/utils.py
edmine/model/cognitive_diagnosis_model/DINA.py
edmine/model/cognitive_diagnosis_model/DLCognitiveDiagnosisModel.py
edmine/model/cognitive_diagnosis_model/HierCDF.py
edmine/model/cognitive_diagnosis_model/HyperCD.py
edmine/model/cognitive_diagnosis_model/IRT.py
edmine/model/cognitive_diagnosis_model/MIRT.py
edmine/model/cognitive_diagnosis_model/NCD.py
edmine-1.0.0.dist-info/licenses/LICENSE
edmine-1.0.0.dist-info/METADATA
edmine-1.0.0.dist-info/WHEEL
edmine-1.0.0.dist-info/top_level.txt
edmine-1.0.0.dist-info/RECORD
