Metadata-Version: 2.4
Name: edmine
Version: 1.0.0
Summary: A library of algorithms for reproducing Knowledge Tracing, Cognitive Diagnosis, Exercise Recommendation and Learning Path Recommendation models.
Author-email: ZhijieXiong <18800118477@163.com>
License: MIT License
Project-URL: Homepage, https://zhijiexiong.github.io/sub-page/pyedmine/document/site/index.html
Requires-Python: >=3.9
License-File: LICENSE
Provides-Extra: dev
Dynamic: license-file
